<?xml version="1.0"?>
<!DOCTYPE hibernate-mapping PUBLIC "-//Hibernate/Hibernate Mapping DTD 3.0//EN"
"http://hibernate.sourceforge.net/hibernate-mapping-3.0.dtd">
<!-- Generated 8 nov. 2011 12:36:52 by Hibernate Tools 3.2.1.GA -->
<hibernate-mapping>
    <class name="domain.user.Users" table="USERS" schema="JORIS.PUECHLONG">
        <id name="idUser" type="short">
            <column name="ID_USER" precision="4" scale="0" />
            <generator class="assigned" />
        </id>
        <property name="loginUser" type="string">
            <column name="LOGIN_USER" length="20" />
        </property>
        <property name="mdpUser" type="string">
            <column name="MDP_USER" length="20" />
        </property>
    </class>
</hibernate-mapping>
